distribution_regressor/__init__.py
distribution_regressor/distribution_regressor_boosted.py
distribution_regressor/distribution_regressor_rf.py
distribution_regressor/distribution_regressor_rf_single.py
distribution_regressor/distribution_regressor_soft_target.py
distribution_regressor/regressor.py
distribution_regressor-1.3.0.dist-info/licenses/LICENSE
distribution_regressor-1.3.0.dist-info/METADATA
distribution_regressor-1.3.0.dist-info/WHEEL
distribution_regressor-1.3.0.dist-info/top_level.txt
distribution_regressor-1.3.0.dist-info/RECORD
