Metadata-Version: 2.4
Name: distribution-regressor
Version: 1.3.0
Summary: Nonparametric distributional regression using LightGBM
Home-page: https://github.com/guyko81/DistributionRegressor
Author: Gabor Gulyas
Author-email: 
License: MIT
Project-URL: Homepage, https://github.com/guyko81/DistributionRegressor
Project-URL: Documentation, https://github.com/guyko81/DistributionRegressor#readme
Project-URL: Repository, https://github.com/guyko81/DistributionRegressor
Project-URL: Bug Tracker, https://github.com/guyko81/DistributionRegressor/issues
Keywords: machine-learning,regression,distribution,lightgbm,uncertainty
Classifier: Development Status :: 4 - Beta
Classifier: Intended Audience :: Science/Research
Classifier: Intended Audience :: Developers
Classifier: Topic :: Scientific/Engineering :: Artificial Intelligence
Classifier: Topic :: Scientific/Engineering :: Mathematics
Classifier: License :: OSI Approved :: MIT License
Classifier: Programming Language :: Python :: 3
Classifier: Programming Language :: Python :: 3.8
Classifier: Programming Language :: Python :: 3.9
Classifier: Programming Language :: Python :: 3.10
Classifier: Programming Language :: Python :: 3.11
Classifier: Programming Language :: Python :: 3.12
Requires-Python: >=3.8
License-File: LICENSE
Requires-Dist: numpy>=1.20.0
Requires-Dist: pandas>=1.3.0
Requires-Dist: scipy>=1.7.0
Requires-Dist: scikit-learn>=1.0.0
Requires-Dist: lightgbm>=3.0.0
Requires-Dist: joblib>=1.0.0
Provides-Extra: dev
Requires-Dist: pytest>=7.0.0; extra == "dev"
Requires-Dist: pytest-cov>=3.0.0; extra == "dev"
Requires-Dist: black>=22.0.0; extra == "dev"
Requires-Dist: flake8>=4.0.0; extra == "dev"
Dynamic: home-page
Dynamic: license-file
Dynamic: requires-python
